python_mcp/__init__.py
python_mcp/api_client.py
python_mcp/mcp_server.py
python_mcp-1.0.1.dist-info/METADATA
python_mcp-1.0.1.dist-info/WHEEL
python_mcp-1.0.1.dist-info/entry_points.txt
python_mcp-1.0.1.dist-info/top_level.txt
python_mcp-1.0.1.dist-info/RECORD
