Metadata-Version: 2.2
Name: python-mcp
Version: 1.0.1
Summary: MCP提示词管理服务
Author-email: Chengfeng <chengfeng@example.com>
License: MIT
Classifier: Programming Language :: Python :: 3
Classifier: License :: OSI Approved :: MIT License
Classifier: Operating System :: OS Independent
Requires-Python: >=3.8
Requires-Dist: requests>=2.28.0
Requires-Dist: urllib3>=1.26.0
